odoo/addons/partner_readonly_security/README.rst
odoo/addons/partner_readonly_security/__init__.py
odoo/addons/partner_readonly_security/__manifest__.py
odoo/addons/partner_readonly_security/i18n/es.po
odoo/addons/partner_readonly_security/i18n/it.po
odoo/addons/partner_readonly_security/i18n/partner_readonly_security.pot
odoo/addons/partner_readonly_security/models/__init__.py
odoo/addons/partner_readonly_security/models/res_partner.py
odoo/addons/partner_readonly_security/readme/CONTEXT.md
odoo/addons/partner_readonly_security/readme/CONTRIBUTORS.md
odoo/addons/partner_readonly_security/readme/DESCRIPTION.md
odoo/addons/partner_readonly_security/readme/USAGE.md
odoo/addons/partner_readonly_security/security/partner_readonly_security_security.xml
odoo/addons/partner_readonly_security/static/description/icon.png
odoo/addons/partner_readonly_security/static/description/index.html
odoo/addons/partner_readonly_security/tests/__init__.py
odoo/addons/partner_readonly_security/tests/test_partner_readonly_security.py
odoo_addon_partner_readonly_security-17.0.1.0.0.5.dist-info/METADATA
odoo_addon_partner_readonly_security-17.0.1.0.0.5.dist-info/WHEEL
odoo_addon_partner_readonly_security-17.0.1.0.0.5.dist-info/top_level.txt
odoo_addon_partner_readonly_security-17.0.1.0.0.5.dist-info/RECORD
